{"cameraMode":{"drawMode":0,"name":"Shaded","section":"Shading Mode"},"sceneLighting":true,"audioPlay":false,"sceneViewState":{"m_AlwaysRefresh":false,"showFog":true,"showSkybox":true,"showFlares":true,"showImageEffects":true,"showParticleSystems":true,"showVisualEffectGraphs":true,"m_FxEnabled":true},"in2DMode":false,"pivot":{"x":-1.232564926147461,"y":3.017162322998047,"z":1.9243342876434327},"rotation":{"x":-0.052084892988204959,"y":0.8194949626922607,"z":-0.07544892281293869,"w":-0.5657128691673279},"size":4.526769638061523,"orthographic":false}